{
  "updatedAt": "2026-02-13",
  "source": "barchart_scrape",
  "items": [
    {
      "symbol": "ZCH26",
      "name": "Corn",
      "month": "Mar '26",
      "last": 430.25,
      "change": -1,
      "percent": -0.23
    },
    {
      "symbol": "ZWH26",
      "name": "Wheat",
      "month": "Mar '26",
      "last": 550.5,
      "change": -2,
      "percent": -0.36
    },
    {
      "symbol": "ZSK26",
      "name": "Soybeans",
      "month": "May '26",
      "last": 1150.25,
      "change": -2,
      "percent": -0.17
    }
  ]
}
